importer/__init__.py
importer/admin.py
importer/apps.py
importer/classes.py
importer/events.py
importer/exceptions.py
importer/importers.py
importer/literals.py
importer/permissions.py
importer/queues.py
importer/serializers.py
importer/tasks.py
importer/urls.py
importer/api_views/__init__.py
importer/api_views/api_view_mixins.py
importer/api_views/import_setup_api_views.py
importer/api_views/import_setup_item_api_views.py
importer/forms/__init__.py
importer/forms/filer_forms.py
importer/forms/form_mixins.py
importer/forms/import_setup_forms.py
importer/forms/import_setup_item_forms.py
importer/icons/__init__.py
importer/icons/import_setup_filer_icons.py
importer/icons/import_setup_icons.py
importer/icons/import_setup_item_icons.py
importer/links/__init__.py
importer/links/import_setup_filer_links.py
importer/links/import_setup_item_links.py
importer/links/import_setup_links.py
importer/migrations/0001_initial.py
importer/migrations/0002_auto_20200908_0458.py
importer/migrations/0003_importsetup_metadata_map.py
importer/migrations/0004_auto_20200908_0853.py
importer/migrations/0005_importsetup_state.py
importer/migrations/0006_auto_20200924_0802.py
importer/migrations/0007_auto_20200924_0802.py
importer/migrations/0008_auto_20200924_0903.py
importer/migrations/0009_importsetupaction.py
importer/migrations/0010_remove_importsetup_metadata_map.py
importer/migrations/0011_auto_20201004_0042.py
importer/migrations/0012_importsetupitem_documents.py
importer/migrations/0013_auto_20201225_0155.py
importer/migrations/0014_auto_20201227_0610.py
importer/migrations/0015_auto_20220901_0932.py
importer/migrations/0016_importsetup_item_time_buffer.py
importer/migrations/0017_delete_importsetuplog.py
importer/migrations/0018_auto_20240401_0808.py
importer/migrations/0019_auto_20240402_1101.py
importer/migrations/0020_auto_20240502_1907.py
importer/migrations/0021_migrate_state_codes.py
importer/migrations/0022_auto_20240503_0853.py
importer/migrations/__init__.py
mayan_importer-3.5.dist-info/LICENSE
mayan_importer-3.5.dist-info/METADATA
mayan_importer-3.5.dist-info/WHEEL
mayan_importer-3.5.dist-info/top_level.txt
mayan_importer-3.5.dist-info/RECORD
